<?xml version="1.0" encoding="utf-8"?>
<!--
********************************************************
Caso pratico "Tamponamento" CDA-CH-II
Certificato medico LAINF del medico di famiglia all'attenzione della Suva

History:
2010.05.12: Tony Schaller, medshare GmbH (aus Input Storyboard HL7 CDA-CH-II)
2010.05.17: Tony Schaller, medshare GmbH (Einfügen finaler OIDs)
2015.02.09: Tony Schaller, medshare GmbH (Div. Korrekturen zu neuen Schematronregeln)

********************************************************
-->
<?xml-stylesheet type='text/xsl' href='../../../../stylesheets/HL7.ch/CDA-CH/v1.2/cda-ch.xsl'?>
<?xml-stylesheet type='text/css' href='../../../../projects/Suva/eMedidoc/v2.0/suva.css'?>
<ClinicalDocument xsi:schemaLocation="urn:hl7-org:v3 CDA.xsd" xmlns="urn:hl7-org:v3" xmlns:voc="urn:hl7-org:v3/voc" xmlns:xsi="http://www.w3.org/2001/XMLSchema-instance">
	<typeId extension="POCD_HD000040" root="2.16.840.1.113883.1.3"/>
	<templateId extension="2927" root="2.16.756.5.30.1.100.2.1"/>
	<id extension="fbca3d60-a20d-406f-81fe-6ca45b887254" root="2.16.756.5.30.1.100.2"/>
	<code code="51848-0" codeSystem="2.16.840.1.113883.6.1" displayName="Certificato medico LAINF"/>
	<!-- Regel CDLN: Als Sistema di codifica für ClinicalDocument.code ist LOINC (2.16.840.1.113883.6.1) zu verwenden.-->
	<title>Certificato medico LAINF</title>
	<effectiveTime value="20100203"/>
	<confidentialityCode code="N" codeSystem="2.16.840.1.113883.5.25"/>
	<languageCode code="it-CH"/>
	<setId extension="fbca3d60-a20d-406f-81fe-6ca45b887254" root="2.16.756.5.30.1.1.1.1"/>
	<versionNumber value="1"/>
	<recordTarget>
		<patientRole>
			<id extension="8.79462.08.1" root="2.16.756.5.30.1.100.3.1.1"/>
			<!-- Suva OID per numero claim -->
			<id extension="123.73.423.123" root="2.16.756.5.31"/>
			<!-- OID per vecchio n. AVS -->
			<addr use="HP">
				<streetName>Leidensweg</streetName>
				<houseNumber>10</houseNumber>
				<postalCode>9876</postalCode>
				<city>Specimendorf</city>
			</addr>
			<telecom use="HP" value="tel:+41.32.685.12.34"/>
			<telecom use="PUB" value="tel:+41.32.123.77.88"/>
			<patient>
				<name>
					<given>Max</given>
					<family>MUSTER</family>
				</name>
				<administrativeGenderCode code="M" codeSystem="2.16.840.1.113883.5.1"/>
				<birthTime value="19480611"/>
			</patient>
			<providerOrganization>
				<id extension="7608888888888" root="1.3.88"/>
				<name>Dr. med. Allzeit Bereit, Studio collettivo CH</name>
			</providerOrganization>
		</patientRole>
	</recordTarget>
	<author>
		<functionCode code="PCP" codeSystem="2.16.756.5.30.2.1.1.1"/>
		<time value="20100203"/>
		<assignedAuthor>
			<id extension="7608888888888" root="1.3.88"/>
			<addr use="WP">
				<streetName>Doktorgasse</streetName>
				<houseNumber>2</houseNumber>
				<postalCode>8888</postalCode>
				<city>Musterhausen</city>
			</addr>
			<telecom use="PUB" value="tel:+41.32.234.55.66"/>
			<telecom use="PUB" value="fax:+41.32.234.66.77"/>
			<telecom use="PUB" value="mailto:bereit@gruppenpraxis.ch"/>
			<telecom use="PUB" value="http://www.gruppenpraxis.ch"/>
			<assignedPerson>
				<name>
					<prefix>Dr. med.</prefix>
					<given>Allzeit</given>
					<family>Bereit</family>
					<suffix>Specialista in medicina generale</suffix>
				</name>
			</assignedPerson>
			<representedOrganization>
				<name>Studio collettivo CH</name>
				<addr use="WP">
					<streetName>Doktorgasse</streetName>
					<houseNumber>2</houseNumber>
					<postalCode>8888</postalCode>
					<city>Musterhausen</city>
				</addr>
			</representedOrganization>
		</assignedAuthor>
	</author>
	<custodian>
		<assignedCustodian>
			<representedCustodianOrganization>
				<id extension="7608888888888" root="1.3.88"/>
				<name>Studio collettivo CH</name>
				<addr use="WP">
					<streetName>Doktorgasse</streetName>
					<houseNumber>2</houseNumber>
					<postalCode>8888</postalCode>
					<city>Musterhausen</city>
				</addr>
			</representedCustodianOrganization>
		</assignedCustodian>
	</custodian>
	<informationRecipient typeCode="PRCP">
		<intendedRecipient>
			<id extension="A99" root="2.16.756.5.30.1.100.1.2.3"/>
			<informationRecipient>
				<name>Agenzia Suva Musterhausen</name>
			</informationRecipient>
			<receivedOrganization>
				<addr use="WP">
					<streetAddressLine>Rainweg 53</streetAddressLine>
					<postalCode>8888</postalCode>
					<city>Musterhausen</city>
				</addr>
			</receivedOrganization>
		</intendedRecipient>
	</informationRecipient>
	<legalAuthenticator>
		<time value="20100203"/>
		<signatureCode code="S"/>
		<assignedEntity>
			<id extension="2099988871229" root="1.3.88"/>
			<id extension="7608888888888" root="1.3.88"/>
			<assignedPerson>
				<name>
					<prefix>Dr. med.</prefix>
					<given>Allzeit</given>
					<family>Bereit</family>
				</name>
			</assignedPerson>
		</assignedEntity>
	</legalAuthenticator>
	<participant typeCode='IND'>
		<templateId root="2.16.756.5.30.1.1.1.1.1" extension="CDA-CH.Head.Empl"/>
		<templateId root='1.3.6.1.4.1.19376.1.5.3.1.2.2'/>
		<time>
			<low nullFlavor='UNK' />
			<high nullFlavor='UNK' />
		</time>
		<associatedEntity classCode='CON'>
			<id extension='987654321' root='2.16.756.5.30.1.100.9999999'/>
			<code code='EMPLOYER' codeSystem='1.3.5.1.4.1.19376.1.5.3.3' codeSystemName='IHERoleCode'/>
			<associatedPerson>
				<name nullFlavor='UNK' />
			</associatedPerson>
			<scopingOrganization>
				<name>Brötligeber AG</name>
				<telecom nullFlavor='UNK' />
				<addr use="WP">
					<streetAddressLine>Lohnbüro</streetAddressLine>
					<streetAddressLine>Postfach</streetAddressLine>
					<postalCode>8888</postalCode>
					<city>Zürich</city>
				</addr>
			</scopingOrganization>
		</associatedEntity>
	</participant>
	<component>
		<structuredBody>
			<component>
				<section>
					<templateId root="2.16.756.5.30.1.100.2.2.1" extension="eMedidoc.SchadenInfo"/>
					<title>Informazioni relative al sinistro</title>
					<text>
						<table>
							<tbody>
								<tr>
									<td>Data del sinistro</td>
									<td>01.02.2010</td>
									<td>
										Notificato come infortunio
									</td>
								</tr>
								<tr>
									<td>
									Primo trattamento<br/>da medico riempimento
								</td>
								<td>01.02.2010</td>
							</tr>
						</tbody>
					</table>
				</text>
				<entry>
					<!-- eMedidoc Observation Template: Motivo del trattamento -->
					<observation classCode="OBS" moodCode="EVN">
						<templateId root="2.16.756.5.30.1.100.2.2.1" extension="eMedidoc.SchadenInfoL3"/>
						<!-- numero claim -->
						<id extension="8.79462.08.1" root="2.16.756.5.30.1.100.3.1.1"/>
						<!-- Tipo di registrazione -->
						<code code="U" codeSystem="2.16.756.5.30.1.100.3.2.2" displayName="Infortunio"/>
						<!-- Data del sinistro -->
						<effectiveTime value="20100201"/>
					</observation>
				</entry>
				<entry>
					<!-- eMedidoc Encounter Template: Primo trattamento -->
					<encounter classCode="ENC" moodCode="EVN">
						<templateId root="2.16.756.5.30.1.100.2.2.1" extension="eMedidoc.ErstbehandlungL3"/>
						<!-- Inconvenienti del primo trattamento -->
						<code code="N" codeSystem="2.16.756.5.30.1.100.3.2.3" displayName="in studio, durante l'orario di apertura"/>
						<!-- Data e eventualmente Tempo del trattamento iniziale -->
						<effectiveTime value="20100201"/>
						<!-- Trattamento iniziale da medico riempimento -->
						<performer>
							<assignedEntity>
								<id nullFlavor="UNK" />
								<assignedPerson>
									<name>
										<prefix>Dr. med.</prefix>
										<given>Allzeit</given>
										<family>Bereit</family>
										<suffix>Specialista in medicina generale</suffix>
									</name>
								</assignedPerson>
								<representedOrganization>
									<name>Studio collettivo CH, Dr. med. Allzeit Bereit, Medicina generale FMH</name>
									<addr use="WP">
										<streetName>Doktorgasse</streetName>
										<houseNumber>2</houseNumber>
										<postalCode>8888</postalCode>
										<city>Musterhausen</city>
									</addr>
								</representedOrganization>
							</assignedEntity>
						</performer>
					</encounter>
				</entry>
			</section>
		</component>
		<component>
			<section>
				<templateId root="2.16.756.5.30.1.100.2" extension="Suva.2927.AngabenPat"/>
				<title>Dichiarazioni del paziente</title>
				<text>
					Il 1.2.2010, mentre guidava la sua auto sulla strada fra Specimendorf e Musterstadt improvviso attacco di nausea, vertigini e tachicardia. 
					Perciò brusca frenata con conseguente tamponamento da parte del veicolo successivo.
					All'inizio soltanto dolori lancinanti alla nuca e vertigini, nel corso degli ultimi giorni dolori sempre più intensi nella regione della nuca con irradiazioni nell'occipite.
				</text>
			</section>
		</component>
		<component>
			<section>
				<templateId root="2.16.756.5.30.1.100.2" extension="Suva.2927.Allgemeinzustand"/>
				<title>Stato generale</title>
				<text>
					<table>
						<tbody>
							<tr>
								<td>Osservazioni particolari (stato mentale, alcool, droghe, ecc.):</td>
								<td>stato generale lievemente compromesso, nessun indizio di consumo di alcolici o droghe</td>
							</tr>
							<tr>
								<td>Postumi di malattie e infortuni e anomalie fisiche (Invalidità):</td>
								<td>Nessuna</td>
							</tr>
						</tbody>
					</table>
				</text>
				<entry>
					<!-- eMedidoc Observation Template: Besondere Wahrnehmungen -->
					<observation classCode="OBS" moodCode="EVN">
						<templateId root="2.16.756.5.30.1.100.2.2.1" extension="eMedidoc.BesoWahrn"/>
						<!-- Specifiche strutturato -->
						<code code="Y" codeSystem="2.16.756.5.30.2.1.1.3.1" />
						<text>stato generale lievemente compromesso, nessun indizio di consumo di alcolici o droghe</text>
					</observation>
				</entry>
				<entry>
					<!-- eMedidoc Observation Template: Folgen von -->
					<observation classCode="OBS" moodCode="EVN">
						<templateId root="2.16.756.5.30.1.100.2.2.1" extension="eMedidoc.FolgenVon"/>
						<!-- Specifiche strutturato -->
						<code code="N" codeSystem="2.16.756.5.30.2.1.1.3.1" />
					</observation>
				</entry>
			</section>
		</component>
		<component>
			<section>
				<templateId root="2.16.756.5.30.1.100.2" extension="Suva.2927.Befund"/>
				<title>Referto</title>
				<text>
					<table>
						<tbody>
							<tr>
								<td>Referto locale:</td>
								<td>
									Ridotta mobilità del rachide cervicale a causa del dolore, con dolore al termine della rotazione verso destra. Nessun segno neurologico anormale.
								</td>
							</tr>
							<tr>
								<td>Referto radiologico:</td>
								<td>Esame radiologico convenzionale del rachide cervicale nell'ospedale cantonale il 1.2.2010: leggera scoliosi destro convessa, nessuna frattura.</td>
							</tr>
						</tbody>
					</table>
				</text>
				<entry>
					<!-- eMedidoc Observation Template: Referto locale -->
					<observation classCode="OBS" moodCode="EVN">
						<templateId root="2.16.756.5.30.1.100.2.2.1" extension="eMedidoc.Lokalbefund"/>
						<code nullFlavor='UNK'/>
						<text>Ridotta mobilità del rachide cervicale a causa del dolore, con dolore al termine della rotazione verso destra. Nessun segno neurologico anormale.</text>
					</observation>
				</entry>
				<entry>
					<!-- eMedidoc Observation Template: Referto radiologico -->
					<observation classCode="OBS" moodCode="EVN">
						<templateId root="2.16.756.5.30.1.100.2.2.1" extension="eMedidoc.Röntgenbefund"/>
						<!-- Specifiche strutturato -->
						<code code="Y" codeSystem="2.16.756.5.30.1.100.3.2.3" />
						<text>Esame radiologico convenzionale del rachide cervicale nell'ospedale cantonale il 1.2.2010: leggera scoliosi destro convessa, nessuna frattura.</text>
					</observation>
				</entry>
			</section>
		</component>
		<component>
			<section>
				<templateId root="2.16.756.5.30.1.1.1.1.1" extension="CDA-CH.Body.DiagList"/>
				<code codeSystem="2.16.840.1.113883.6.1" code="29548-5" />
				<title>Diagnosi</title>
				<text>
					<table>
						<tbody>
							<tr>
								<th>Diagnosi</th>
								<th>Code</th>
								<th>Sistema di codifica</th>
								<th>Giudicato da</th>
							</tr>
							<tr>
								<td>Distorsione del rachide cervicale dopo tamponamento il 1.2.2010</td>
								<td>S13.4</td>
								<td>ICD-10</td>
								<td>
									Dr. med. Allzeit Bereit
								</td>
							</tr>
						</tbody>
					</table>
				</text>
				<entry>
					<!-- CDA-CH Observation Template: Diagnosi (L1; Testo libero) -->
					<observation classCode="OBS" moodCode="EVN">
						<templateId root="2.16.756.5.30.1.1.1.1.1" extension="CDA-CH.Body.DiagL1"/>
						<!-- für Diagnosi im Level 3:-->
						<code code="S13.4" codeSystem="1.2.276.0.76.5.388" />
						<!-- icd10gm2011 DIMDI -->
						<text>Distorsione del rachide cervicale dopo tamponamento il 1.2.2010</text>
						<effectiveTime value='20100203'/>
						<!-- für Diagnosi im Level 3:-->
						<performer>
							<assignedEntity>
								<id nullFlavor="UNK" />
								<assignedPerson>
									<name>
										<prefix>Dr. med.</prefix>
										<given>Allzeit</given>
										<family>Bereit</family>
										<suffix>Specialista in medicina generale</suffix>
									</name>
								</assignedPerson>
							</assignedEntity>
						</performer>
					</observation>
				</entry>
			</section>
		</component>
		<component>
			<section>
				<templateId root="2.16.756.5.30.1.100.2" extension="Suva.2927.Kausalität"/>
				<title>Causalità</title>
				<text>
					<table>
						<tbody>
							<tr>
								<td>Sussistono unicamente le conseguenze dell'infortunio:</td>
								<td>Si</td>
							</tr>
							<tr>
								<td>Motivazione:</td>
								<td></td>
							</tr>
						</tbody>
					</table>
				</text>
				<entry>
					<!-- CDA-CH Observation Template: Unfallfolgen -->
					<observation classCode="OBS" moodCode="EVN">
						<templateId root="2.16.756.5.30.1.100.2.2.1" extension="eMedidoc.Unfallfolgen"/>
						<!-- Specifiche strutturato "unicamente le conseguenze dell'infortunio" -->
						<code code="Y" codeSystem="2.16.756.5.30.1.100.3.2.3" />
					</observation>
				</entry>
			</section>
		</component>
		<component>
			<section>
				<templateId root="2.16.756.5.30.1.100.2" extension="Suva.2927.Therapie"/>
				<title>Terapia</title>
				<text>
					<table>
						<tbody>
							<tr>
								<td>Misure:</td>
								<td>analgesici, fisioterapia</td>
							</tr>
							<tr>
								<td>Paziente ospedalizzato:</td>
								<td>
									No
								</td>
							</tr>
							<tr>
								<td>Circostanze particolari che potrebbero influire negativamente sul decorso della guarigione:</td>
								<td>Nessun dettaglio</td>
							</tr>
						</tbody>
					</table>
				</text>
				<entry>
					<!-- CDA-CH Procedure Template: Therapiemassnahme -->
					<procedure moodCode="EVN" classCode="PROC">
						<templateId root="2.16.756.5.30.1.100.2.2.1" extension="eMedidoc.TherapieMassnahme"/>
						<code nullFlavor="UNK" />
						<text>analgesici, fisioterapia</text>
					</procedure>
				</entry>
				<entry>
					<!-- CDA-CH Procedure Template: Paziente ospedalizzato -->
					<procedure moodCode="EVN" classCode="PROC">
						<templateId root="2.16.756.5.30.1.100.2.2.1" extension="eMedidoc.PatHospitalisiert"/>
						<!-- Specifiche strutturato -->
						<code code="N" codeSystem="2.16.756.5.30.2.1.1.3.1" />
					</procedure>
				</entry>
				<entry>
					<!-- eMedidoc Observation Template: Besondere Umstände -->
					<observation classCode="OBS" moodCode="EVN">
						<templateId root="2.16.756.5.30.1.100.2.2.1" extension="eMedidoc.BesoUmstände"/>
						<!-- Specifiche strutturato -->
						<code code="U" codeSystem="2.16.756.5.30.2.1.1.3.1" />
					</observation>
				</entry>
			</section>
		</component>
		<component>
			<section>
				<templateId root="2.16.756.5.30.1.1.1.1.1" extension="CDA-CH.Body.ArbeitsfähigkeitList"/>
				<code code="X-ATWRK" codeSystem="2.16.840.1.113883.6.1" codeSystemName="LOINC"/>
				<title>Capacità lavorativa</title>
				<text>
					<table>
						<tbody>
							<tr>
								<th>Valida dal</th>
								<th>Durata presenza</th>
								<th>Intensità lavorativa</th>
								<th>Valida al</th>
								<th>Giudicato da</th>
							</tr>
							<tr>
								<td>Data della consultazione</td>
								<td>Orari ragionevoli al giorno nella gestione</td>
								<td>% dell'usuale intensità lavorativa</td>
								<td>Prossima valutazione</td>
								<td/>
							</tr>
							<tr>
								<td>03.02.2010</td>
								<td>0 Ore al giorno</td>
								<td>0%</td>
								<td>07.02.2010</td>
								<td>Dr. med. Allzeit Bereit</td>
							</tr>
						</tbody>
					</table>
				</text>
				<entry>
					<observation classCode="OBS" moodCode="EVN">
						<templateId root="2.16.756.5.30.1.1.1.1.1" extension="CDA-CH.Body.ArbeitsfähigkeitL3"/>
						<code code="X-ATWRK" codeSystem="2.16.840.1.113883.6.1" codeSystemName="LOINC"/>
						<text>Voll arbeitsfähig ab 3.6.2008</text>
						<statusCode code="completed"/>
						<effectiveTime>
							<low value="20100203"/>
							<high value="20100207"/>
						</effectiveTime>
						<value xsi:type='CE' code="0" codeSystem="2.16.756.5.30.2.1.1.6.1" />
						<interpretationCode code="0" codeSystem="2.16.756.5.30.2.1.1.7.1" />
						<performer>
							<assignedEntity>
								<id nullFlavor="UNK" />
								<assignedPerson>
									<name>
										<prefix>Dr. med.</prefix>
										<given>Allzeit</given>
										<family>Bereit</family>
									</name>
								</assignedPerson>
							</assignedEntity>
						</performer>
					</observation>
				</entry>
			</section>
		</component>
		<component>
			<section>
				<templateId root="2.16.756.5.30.1.100.2.2.1" extension="eMedidoc.BehAbschluss"/>
				<title>Conclusione del trattamento</title>
				<text>
					<table>
						<tbody>
							<tr>
								<td>Conclusione del trattamento:</td>
								<td>no</td>
								<td>
									presumibilmente tra 4 settimane
								</td>
							</tr>
							<tr>
								<td>Ultimo trattamento:</td>
								<td>Dr. med. Allzeit Bereit</td>
								<td>
									Doktorgasse 2, 8888 Musterhausen
								</td>
							</tr>
						</tbody>
					</table>
				</text>
				<entry>
					<!-- eMedidoc Encounter Template: Conclusione del trattamento (moodCode="EVN": definitiv, moodCode="INT": prevista) -->
					<encounter classCode="ENC" moodCode="EVN">
						<templateId root="2.16.756.5.30.1.100.2.2.1" extension="eMedidoc.BehAbschlussL3"/>
						<code code="8649-6" codeSystem="2.16.840.1.113883.6.1" />
						<effectiveTime>
							<low nullFlavor='NA'/>
							<high value='20100303'/>
						</effectiveTime>
						<performer>
							<assignedEntity>
								<id nullFlavor="UNK" />
								<representedOrganization>
									<name>Musterspital</name>
									<addr use="WP">
										<streetName>Hospitalgasse</streetName>
										<houseNumber>2</houseNumber>
										<postalCode>8888</postalCode>
										<city>Musterhausen</city>
									</addr>
								</representedOrganization>
							</assignedEntity>
						</performer>
					</encounter>
				</entry>
			</section>
		</component>
		<component>
			<section>
				<templateId root="2.16.756.5.30.1.1.1.1.1" extension="CDA-CH.Body.Rem"/>
				<templateId root="2.16.756.5.30.1.100.2.2.1" extension="eMedidoc.Rem"/>
				<code code="48767-8" codeSystem="2.16.840.1.113883.6.1" codeSystemName="LOINC"/>
				<title>Osservazioni</title>
				<text>
					<content>Nessuna<br/>
						<br/>
					</content>
					<table>
						<tbody>
							<tr>
								<td>Occupazione di stato:</td>
								<td>Lavoro</td>
							</tr>
						</tbody>
					</table>
				</text>
				<entry>
					<!-- CDA-CH Observation Template: Occupazione di stato -->
					<observation classCode="OBS" moodCode="EVN">
						<templateId root="2.16.756.5.30.1.100.2.2.1" extension="eMedidoc.Erwerbstatus"/>
						<!-- Specifiche strutturato "Occupazione di stato" -->
						<code code="E" codeSystem="2.16.756.5.30.1.100.3.2.4" />
					</observation>
				</entry>
			</section>
		</component>
	</structuredBody>
</component>
</ClinicalDocument>
